{"categories":[{"id":73,"name":"Adventure","created_at":"2018-05-12T08:46:41.527Z","updated_at":"2018-05-12T08:46:41.527Z"},{"id":67,"name":"Drama","created_at":"2018-05-11T01:55:51.421Z","updated_at":"2018-05-11T01:55:51.421Z"},{"id":68,"name":"Action","created_at":"2018-05-11T01:55:51.423Z","updated_at":"2018-05-11T01:55:51.423Z"},{"id":69,"name":"Comedy","created_at":"2018-05-11T01:55:51.426Z","updated_at":"2018-05-11T01:55:51.426Z"},{"id":70,"name":"Documentary","created_at":"2018-05-11T01:55:51.428Z","updated_at":"2018-05-11T01:55:51.428Z"},{"id":71,"name":"Romance","created_at":"2018-05-11T01:55:51.430Z","updated_at":"2018-05-11T01:55:51.430Z"},{"id":72,"name":"Science Fiction","created_at":"2018-05-11T01:55:51.433Z","updated_at":"2018-05-11T01:55:51.433Z"}]}